dotclear_backup_parser/__init__.py
dotclear_backup_parser-0.0.1.dist-info/LICENSE
dotclear_backup_parser-0.0.1.dist-info/METADATA
dotclear_backup_parser-0.0.1.dist-info/WHEEL
dotclear_backup_parser-0.0.1.dist-info/top_level.txt
dotclear_backup_parser-0.0.1.dist-info/RECORD
