Metadata-Version: 2.1
Name: dotclear-backup-parser
Version: 0.0.1
Summary: Module to parse dotclear backup files.
Author-email: Dorian Fevrier <fevrier.dorian@yahoo.fr>
Maintainer-email: Dorian Fevrier <fevrier.dorian@yahoo.fr>
License: GNU GENERAL PUBLIC LICENSE
Keywords: blog,dotclear,backup
Classifier: Development Status :: 2 - Pre-Alpha
Classifier: Intended Audience :: Developers
Classifier: Topic :: File Formats
Classifier: License :: OSI Approved :: GNU General Public License v3 (GPLv3)
Classifier: Programming Language :: Python :: 3
Classifier: Programming Language :: Python :: 3.11
Classifier: Programming Language :: Python :: 3.12
Classifier: Operating System :: OS Independent
Requires-Python: >=3.11
License-File: LICENSE
